ca_certificates/__init__.py
libopenblas-0.7.dist-info/METADATA
libopenblas-0.7.dist-info/WHEEL
libopenblas-0.7.dist-info/top_level.txt
libopenblas-0.7.dist-info/RECORD
