Metadata-Version: 2.4
Name: libopenblas
Version: 0.7
Summary: Dummy libopenblas package for PyPI
Author-email: Your Name <you@example.com>
Requires-Python: >=3.7
